Users/rubelw/virtualenvs/python3/usr/share/devops-menu/devops-menu.yml
Users/rubelw/virtualenvs/python3/usr/share/devops-menu/scripts/test.py
devops_menu/__init__.py
devops_menu/devops_menu.py
devops_menu/exceptions.py
devops_menu/backported/__init__.py
devops_menu/backported/inspect2.py
devops_menu/commons/__init__.py
devops_menu/commons/case_class.py
devops_menu/commons/collection.py
devops_menu/commons/command.py
devops_menu/commons/functional.py
devops_menu/commons/io.py
devops_menu/commons/string.py
devops_menu/commons/terminal.py
devops_menu/commons/types.py
devops_menu/commons/unittest.py
devops_menu/controller/__init__.py
devops_menu/controller/command_executor.py
devops_menu/controller/executor.py
devops_menu/entity/__init__.py
devops_menu/entity/command.py
devops_menu/entity/command_line.py
devops_menu/entity/item.py
devops_menu/entity/menu.py
devops_menu/entity/meta.py
devops_menu/logger/__init__.py
devops_menu/logger/logger.py
devops_menu/logger/system_logger.py
devops_menu/setting/__init__.py
devops_menu/setting/arg_parser.py
devops_menu/setting/loader.py
devops_menu/setting/setting.py
devops_menu/view/__init__.py
devops_menu/view/terminal.py
devops_menu/view/i18n/__init__.py
devops_menu/view/i18n/messages_en.py
devops_menu/view/i18n/messages_ja.py
devops_menu_helper/__init__.py
devops_menu_helper/common.py
devops_menu_helper/config.py
devops_menu_helper/pretty.py
devops_menu-0.5.0.dist-info/METADATA
devops_menu-0.5.0.dist-info/WHEEL
devops_menu-0.5.0.dist-info/entry_points.txt
devops_menu-0.5.0.dist-info/top_level.txt
devops_menu-0.5.0.dist-info/RECORD
