Metadata-Version: 2.1
Name: devops-menu
Version: 0.5.0
Summary: Menu system for Managing AWS Accounts
Home-page: UNKNOWN
Author: Will Rubel
Author-email: willrubel@gmail.com
Maintainer: Will Rubel
Maintainer-email: willrubel@gmail.com
License: Apache 2.0 License
Keywords: AWS CLI AWSCLI Boto Boto3
Platform: UNKNOWN
Classifier: Development Status :: 4 - Beta
Classifier: Operating System :: POSIX
Classifier: Operating System :: MacOS :: MacOS X
Classifier: Intended Audience :: Developers
Classifier: Intended Audience :: System Administrators
Classifier: Intended Audience :: Information Technology
Classifier: License :: OSI Approved :: Apache Software License
Classifier: Natural Language :: English
Classifier: Programming Language :: Python :: 2.7
Classifier: Topic :: System :: Systems Administration
Requires-Dist: awslimitchecker (>=2.0.0)
Requires-Dist: boto3 (>=1.4.2)
Requires-Dist: botocore (>=1.4.85)
Requires-Dist: boto (>=2.44.0)
Requires-Dist: aws-requests-auth
Requires-Dist: Elasticsearch
Requires-Dist: pyyaml
Requires-Dist: six
Requires-Dist: jinja2 (>=2.6)
Requires-Dist: pycrypto
Requires-Dist: paramiko
Requires-Dist: configparser
Requires-Dist: pathlib
Requires-Dist: requests
Requires-Dist: bson
